lampy/__init__.py
lampy/lampy.py
magic_lampy-0.0.0a0.dist-info/LICENSE
magic_lampy-0.0.0a0.dist-info/METADATA
magic_lampy-0.0.0a0.dist-info/WHEEL
magic_lampy-0.0.0a0.dist-info/entry_points.txt
magic_lampy-0.0.0a0.dist-info/top_level.txt
magic_lampy-0.0.0a0.dist-info/RECORD
