Metadata-Version: 2.1
Name: magic-lampy
Version: 0.0.0a0
Summary: A PyTorch framework for researchers and developers with deadline.
Home-page: https://github.com/MagicLamPy/MagicLamPy
Author: Shotaro Kataoka, Masashi Oba
Author-email: shotaro.kata@gmail.com
License: MIT
Keywords: Deep Learning,framework,PyTorch,Machine Learning
Platform: UNKNOWN
Classifier: Programming Language :: Python
Classifier: Programming Language :: Python :: 3
Classifier: Programming Language :: Python :: 3.5
Classifier: Programming Language :: Python :: 3.6
Classifier: Programming Language :: Python :: 3.7
Classifier: Programming Language :: Python :: 3.8
Classifier: License :: OSI Approved :: MIT License
Classifier: Operating System :: OS Independent
Requires-Python: >=3.5
